CHANGELOG.md
LICENSE
README.md
django_scrubber/__init__.py
django_scrubber/admin.py
django_scrubber/apps.py
django_scrubber/models.py
django_scrubber/scrubbers.py
django_scrubber/management/__init__.py
django_scrubber/management/commands/__init__.py
django_scrubber/management/commands/scrub_data.py
django_scrubber/management/commands/scrub_validation.py
django_scrubber/migrations/0001_initial.py
django_scrubber/migrations/__init__.py
django_scrubber/services/__init__.py
django_scrubber/services/validator.py
django_scrubber/tests/__init__.py
django_scrubber/tests/test_models.py
django_scrubber/tests/test_scrub_data.py
django_scrubber/tests/test_scrub_validator.py
django_scrubber/tests/test_scrubbers.py
django_scrubber/tests/test_settings.py
django_scrubber/tests/services/__init__.py
django_scrubber/tests/services/test_validator.py
django_scrubber-6.0.0.dist-info/METADATA
django_scrubber-6.0.0.dist-info/WHEEL
django_scrubber-6.0.0.dist-info/licenses/LICENSE
django_scrubber-6.0.0.dist-info/RECORD
