Metadata-Version: 2.4
Name: django-scrubber
Version: 6.0.0
Summary: Data anonymizer for Django
Project-URL: Homepage, https://github.com/RegioHelden/django-scrubber
Project-URL: Documentation, https://github.com/RegioHelden/django-scrubber/blob/main/README.md
Project-URL: Repository, https://github.com/RegioHelden/django-scrubber.git
Project-URL: Issues, https://github.com/RegioHelden/django-scrubber/issues
Project-URL: Changelog, https://github.com/RegioHelden/django-scrubber/blob/main/CHANGELOG.md
Author-email: RegioHelden GmbH <opensource@regiohelden.de>
Maintainer-email: RegioHelden GmbH <opensource@regiohelden.de>
License-Expression: MIT
License-File: LICENSE
Keywords: anonymize,data protection,django,gdpr,scrub,scrubber
Classifier: Development Status :: 5 - Production/Stable
Classifier: Environment :: Web Environment
Classifier: Framework :: Django
Classifier: Intended Audience :: Developers
Classifier: License :: OSI Approved :: MIT License
Classifier: Operating System :: OS Independent
Classifier: Programming Language :: Python
Classifier: Programming Language :: Python :: 3
Classifier: Programming Language :: Python :: 3.10
Classifier: Programming Language :: Python :: 3.11
Classifier: Programming Language :: Python :: 3.12
Classifier: Programming Language :: Python :: 3.13
Classifier: Programming Language :: Python :: 3.14
Classifier: Topic :: Software Development
Classifier: Topic :: Software Development :: Libraries :: Python Modules
Requires-Python: >=3.10
Requires-Dist: django<6.1,>=4.2
Requires-Dist: faker>=20.0.0
